policy_calculator/__init__.py
policy_calculator/calculate.py
policy_calculator-0.1.0.dist-info/METADATA
policy_calculator-0.1.0.dist-info/WHEEL
policy_calculator-0.1.0.dist-info/top_level.txt
policy_calculator-0.1.0.dist-info/RECORD
