Metadata-Version: 2.1
Name: policy-calculator
Version: 0.1.0
Summary: A library for calculating policy prices based on various factors.
Home-page: https://github.com/yourusername/policy_calculator
Author: Your Name
Author-email: your.email@example.com
License: MIT
Classifier: Programming Language :: Python :: 3
Classifier: License :: OSI Approved :: MIT License
Classifier: Programming Language :: Python :: 3.8
Requires-Python: >=3.6
